mhctyper/__init__.py
mhctyper/__main__.py
mhctyper/_version.py
mhctyper/cli.py
mhctyper/hla_allele.py
mhctyper/logger.py
mhctyper/mhctyper.py
mhctyper/py.typed
mhctyper/score_alleles.py
mhctyper/utils.py
mhctyper-0.1.7.dist-info/METADATA
mhctyper-0.1.7.dist-info/WHEEL
mhctyper-0.1.7.dist-info/entry_points.txt
mhctyper-0.1.7.dist-info/RECORD
