Metadata-Version: 2.3
Name: mhctyper
Version: 0.1.7
Summary: MHC Class I and II typer based on polysolver algorithm.
Project-URL: Source, https://github.com/svm-zhang/mhctyper
Project-URL: Documentation, https://svm-zhang.github.io/mhctyper/
Project-URL: Issues, https://github.com/svm-zhang/mhctyper/issues
Author-email: Simo Zhang <svm.zhang@gmail.com>
Maintainer-email: Simo Zhang <svm.zhang@gmail.com>
License: MIT
Keywords: HLA typing,bioinformatics,genomics,sequencing
Classifier: Development Status :: 4 - Beta
Classifier: Intended Audience :: Developers
Classifier: License :: OSI Approved :: MIT License
Classifier: Operating System :: OS Independent
Classifier: Programming Language :: Python :: 3 :: Only
Classifier: Programming Language :: Python :: 3.10
Classifier: Programming Language :: Python :: 3.11
Classifier: Programming Language :: Python :: 3.12
Classifier: Programming Language :: Python :: 3.13
Classifier: Topic :: Scientific/Engineering :: Bio-Informatics
Classifier: Topic :: Software Development :: Libraries
Requires-Python: >=3.10
Requires-Dist: numpy>=2.1.1
Requires-Dist: polars>=1.7.0
Requires-Dist: pysam>=0.22.1
Requires-Dist: tinyscibio>=0.4.1
Requires-Dist: tqdm>=4.66.5
